sctrend/__init__.py
sctrend/dataset.py
sctrend/exp.py
sctrend/ipcw.py
sctrend/modules_SNV.py
sctrend/utils.py
sctrend/workflow.py
sctrend-0.1.2.dist-info/licenses/LICENSE
sctrend-0.1.2.dist-info/METADATA
sctrend-0.1.2.dist-info/WHEEL
sctrend-0.1.2.dist-info/top_level.txt
sctrend-0.1.2.dist-info/RECORD
