Metadata-Version: 2.4
Name: sctrend
Version: 0.1.2
Summary: scTREND: An annotation-free single-cell time-resolved and condition-dependent hazard model
Author-email: Shintaro Yuki <shin1997research@gmail.com>
License: MIT License
Project-URL: Homepage, https://github.com/R301Carbine/scTREND
Project-URL: Issues, https://github.com/R301Carbine/scTREND/issues
Keywords: bioinformatics,single-cell
Classifier: License :: OSI Approved :: MIT License
Classifier: Operating System :: OS Independent
Classifier: Programming Language :: Python :: 3
Classifier: Programming Language :: Python :: 3.10
Classifier: Programming Language :: Python :: 3.11
Classifier: Programming Language :: Python :: 3.12
Classifier: Topic :: Scientific/Engineering :: Bio-Informatics
Requires-Python: >=3.8.16
License-File: LICENSE
Requires-Dist: torch>=1.13.1
Requires-Dist: lifelines>=0.27.8
Requires-Dist: scanpy>=1.9.5
Requires-Dist: pandas>=1.5.3
Requires-Dist: numpy>=1.23.5
Requires-Dist: matplotlib>=3.7.2
Requires-Dist: scipy>=1.10.1
Provides-Extra: dev
Requires-Dist: pytest>=8; extra == "dev"
Requires-Dist: build>=1.2; extra == "dev"
Requires-Dist: twine>=6.0; extra == "dev"
Requires-Dist: ruff>=0.6; extra == "dev"
Dynamic: license-file
